fakedcm/__init__.py
fakedcm/fakedcm.py
fakedcm-1.0.0.dist-info/METADATA
fakedcm-1.0.0.dist-info/WHEEL
fakedcm-1.0.0.dist-info/entry_points.txt
fakedcm-1.0.0.dist-info/top_level.txt
fakedcm-1.0.0.dist-info/RECORD
