Metadata-Version: 2.1
Name: fakedcm
Version: 1.0.0
Requires-Dist: fake-useragent
